invenio_saml/__init__.py
invenio_saml/config.py
invenio_saml/errors.py
invenio_saml/ext.py
invenio_saml/handlers.py
invenio_saml/invenio_app.py
invenio_saml/proxies.py
invenio_saml/utils.py
invenio_saml/views.py
invenio_saml/invenio_accounts/__init__.py
invenio_saml/invenio_accounts/utils.py
invenio_saml/templates/invenio-saml/login_user.html
invenio_saml/templates/semantic-ui/invenio_saml/login_user.html
invenio_saml/translations/messages.pot
invenio_saml/translations/ar/LC_MESSAGES/messages.po
invenio_saml/translations/bg/LC_MESSAGES/messages.po
invenio_saml/translations/ca/LC_MESSAGES/messages.po
invenio_saml/translations/cs/LC_MESSAGES/messages.po
invenio_saml/translations/da/LC_MESSAGES/messages.po
invenio_saml/translations/de/LC_MESSAGES/messages.po
invenio_saml/translations/el/LC_MESSAGES/messages.po
invenio_saml/translations/es/LC_MESSAGES/messages.po
invenio_saml/translations/et/LC_MESSAGES/messages.po
invenio_saml/translations/fa/LC_MESSAGES/messages.po
invenio_saml/translations/fi/LC_MESSAGES/messages.po
invenio_saml/translations/fr/LC_MESSAGES/messages.po
invenio_saml/translations/hr/LC_MESSAGES/messages.po
invenio_saml/translations/hu/LC_MESSAGES/messages.po
invenio_saml/translations/it/LC_MESSAGES/messages.po
invenio_saml/translations/ja/LC_MESSAGES/messages.po
invenio_saml/translations/ka/LC_MESSAGES/messages.po
invenio_saml/translations/ko/LC_MESSAGES/messages.po
invenio_saml/translations/lt/LC_MESSAGES/messages.po
invenio_saml/translations/no/LC_MESSAGES/messages.po
invenio_saml/translations/pl/LC_MESSAGES/messages.po
invenio_saml/translations/pt/LC_MESSAGES/messages.po
invenio_saml/translations/ro/LC_MESSAGES/messages.po
invenio_saml/translations/ru/LC_MESSAGES/messages.po
invenio_saml/translations/sk/LC_MESSAGES/messages.po
invenio_saml/translations/sv/LC_MESSAGES/messages.po
invenio_saml/translations/tr/LC_MESSAGES/messages.po
invenio_saml/translations/uk/LC_MESSAGES/messages.po
invenio_saml/translations/zh_CN/LC_MESSAGES/messages.po
invenio_saml-1.2.1.dist-info/licenses/AUTHORS.rst
invenio_saml-1.2.1.dist-info/licenses/LICENSE
invenio_saml-1.2.1.dist-info/METADATA
invenio_saml-1.2.1.dist-info/WHEEL
invenio_saml-1.2.1.dist-info/entry_points.txt
invenio_saml-1.2.1.dist-info/top_level.txt
invenio_saml-1.2.1.dist-info/RECORD
