Metadata-Version: 2.4
Name: invenio-saml
Version: 1.2.1
Summary: "Invenio module that provides SAML integration."
Home-page: https://github.com/inveniosoftware/invenio-saml
Author: Esteban J. Garcia Gabancho
Author-email: info@inveniosoftware.org
License: MIT
Keywords: invenio SSO SAML
Platform: any
Classifier: Development Status :: 5 - Production/Stable
Requires-Python: >=3.7
License-File: LICENSE
License-File: AUTHORS.rst
Requires-Dist: invenio-accounts<7.0.0,>=1.4.5
Requires-Dist: uritools>=2.2.0
Requires-Dist: python3-saml>=1.5.0
Provides-Extra: tests
Requires-Dist: pytest-black-ng>=0.4.0; extra == "tests"
Requires-Dist: invenio-app<3.0.0,>=1.3.0; extra == "tests"
Requires-Dist: invenio-mail<3.0.0,>=1.0.0; extra == "tests"
Requires-Dist: invenio-userprofiles<5.0.0,>=1.0.0; extra == "tests"
Requires-Dist: mock>=2.0.0; extra == "tests"
Requires-Dist: redis>=2.10.5; extra == "tests"
Requires-Dist: pytest-invenio<4.0.0,>=2.1.0; extra == "tests"
Requires-Dist: pytest-freezegun>=0.2.0; extra == "tests"
Requires-Dist: invenio-oauthclient<5.0.0,>=1.5.1; extra == "tests"
Requires-Dist: Sphinx>=4.5.0; extra == "tests"
Requires-Dist: invenio-db[mysql,postgresql,versioning]<3.0.0,>=1.0.9; extra == "tests"
Requires-Dist: xmlsec<=1.3.14; extra == "tests"
Requires-Dist: lxml<=5.2.1; extra == "tests"
Dynamic: license-file
